{
    "tags": [
        {
            "id": "72997f0dc33cf7f6d85ce55a",
            "slug": "product",
            "name": "產品",
            "url": "https://www.addnewfolder.com/tag/product"
        },
        {
            "id": "9f9bef82cbaf1807736c26af",
            "slug": "ai",
            "name": "AI",
            "url": "https://www.addnewfolder.com/tag/ai"
        },
        {
            "id": "157842bd607e40130e5fed9d",
            "slug": "business",
            "name": "商業",
            "url": "https://www.addnewfolder.com/tag/business"
        },
        {
            "id": "419594915204e8c7076227c1",
            "slug": "tech",
            "name": "科技",
            "url": "https://www.addnewfolder.com/tag/tech"
        },
        {
            "id": "04903d9f5c46eea05169950d",
            "slug": "design",
            "name": "設計",
            "url": "https://www.addnewfolder.com/tag/design"
        },
        {
            "id": "e232d700cb8f4440bd10c936",
            "slug": "unicorn",
            "name": "新創",
            "url": "https://www.addnewfolder.com/tag/unicorn"
        },
        {
            "id": "f7aa373d98e75cfcb6f7f120",
            "slug": "3c",
            "name": "3C",
            "url": "https://www.addnewfolder.com/tag/3c"
        },
        {
            "id": "ab8c1fb7730fb05103a06954",
            "slug": "management",
            "name": "管理",
            "url": "https://www.addnewfolder.com/tag/management"
        },
        {
            "id": "7da4db74a2b4711ea0555fac",
            "slug": "travel",
            "name": "旅遊",
            "url": "https://www.addnewfolder.com/tag/travel"
        },
        {
            "id": "8749b9089a565be7b9c77a35",
            "slug": "hongkong",
            "name": "香港",
            "url": "https://www.addnewfolder.com/tag/hongkong"
        },
        {
            "id": "409aba13893ef35ba4d02be1",
            "slug": "hongkong",
            "name": "HongKong",
            "url": "https://www.addnewfolder.com/tag/hongkong"
        },
        {
            "id": "e5a847ae8c2106ba75841f20",
            "slug": "okinawa",
            "name": "沖繩",
            "url": "https://www.addnewfolder.com/tag/okinawa"
        },
        {
            "id": "f8f237e4aa5b54eb78f9031b",
            "slug": "okinawa",
            "name": "Okinawa",
            "url": "https://www.addnewfolder.com/tag/okinawa"
        },
        {
            "id": "a6ccdb7b16b6af235bebd7e6",
            "slug": "social",
            "name": "社群經營",
            "url": "https://www.addnewfolder.com/tag/social"
        },
        {
            "id": "531213121a52310e6be92555",
            "slug": "dataanalysis",
            "name": "數據分析",
            "url": "https://www.addnewfolder.com/tag/dataanalysis"
        },
        {
            "id": "eebede6e767271dae79d2ee9",
            "slug": "reading",
            "name": "讀文心得",
            "url": "https://www.addnewfolder.com/tag/reading"
        }
    ],
    "meta": {
        "pagination": {
            "page": 1,
            "limit": 10000,
            "pages": 1,
            "total": 16,
            "next": null,
            "prev": null
        }
    }
}